reversion_extras/views.py
reversion_extras/version.py
reversion_extras/apps.py
reversion_extras/__init__.py
django_reversion_extras-0.0.2.dist-info/WHEEL
django_reversion_extras-0.0.2.dist-info/metadata.json
django_reversion_extras-0.0.2.dist-info/METADATA
django_reversion_extras-0.0.2.dist-info/DESCRIPTION.rst
django_reversion_extras-0.0.2.dist-info/top_level.txt
django_reversion_extras-0.0.2.dist-info/RECORD
