Metadata-Version: 2.0
Name: django-reversion-extras
Version: 0.0.2
Summary: Extra tools to work with django-reversion
Home-page: https://github.com/luzfcb/django-reversion-extras
Author: Fabio C. Barrionuevo da Luz
Author-email: bnafta@gmail.com
License: BSD
Keywords: django-reversion-extras,reversion,reversion-extras,django-reversion
Platform: UNKNOWN
Classifier: Development Status :: 1 - Planning
Classifier: Framework :: Django
Classifier: Intended Audience :: Developers
Classifier: Natural Language :: English
Classifier: License :: OSI Approved :: BSD License
Classifier: Programming Language :: Python
Classifier: Programming Language :: Python :: 2
Classifier: Programming Language :: Python :: 2.7
Classifier: Programming Language :: Python :: 3
Classifier: Programming Language :: Python :: 3.4
Classifier: Topic :: Software Development
Requires-Dist: django-reversion
Requires-Dist: mock
